Metadata-Version: 2.1
Name: sptr
Version: 1.1.1
Summary: SparseTransformer CUDA ops
Home-page: https://github.com/lh9171338/SparseTransformer
Author: lh9171338
Author-email: lihao2015@whu.edu.cn
Classifier: Programming Language :: Python :: 3
Classifier: License :: OSI Approved :: Apache Software License
Classifier: Operating System :: OS Independent
Requires-Dist: torch
Requires-Dist: timm
Requires-Dist: numpy
Requires-Dist: torch_scatter
Requires-Dist: torch_geometric
